alq-0.0.15.data/scripts/alq
alq-0.0.15.data/scripts/alq.bat
subfunctions/__init__.py
subfunctions/configuration.py
subfunctions/fileSystem.py
subfunctions/owncloud.py
subfunctions/webdavefs.py
alq-0.0.15.dist-info/METADATA
alq-0.0.15.dist-info/WHEEL
alq-0.0.15.dist-info/top_level.txt
alq-0.0.15.dist-info/RECORD
